smoothglue_malware_scan/__init__.py
smoothglue_malware_scan/exceptions.py
smoothglue_malware_scan/scanners/__init__.py
smoothglue_malware_scan/scanners/base.py
smoothglue_malware_scan/scanners/clamav.py
smoothglue_malware_scan-1.0.0.dist-info/licenses/LICENSE
smoothglue_malware_scan-1.0.0.dist-info/licenses/NOTICE
smoothglue_malware_scan-1.0.0.dist-info/METADATA
smoothglue_malware_scan-1.0.0.dist-info/WHEEL
smoothglue_malware_scan-1.0.0.dist-info/top_level.txt
smoothglue_malware_scan-1.0.0.dist-info/RECORD
