Metadata-Version: 2.4
Name: smoothglue_malware_scan
Version: 1.0.0
Summary: A Python utility wrapper for malware scanning libraries
Author: SmoothGlue
Project-URL: Homepage, https://braingu.com/solutions/smoothglue/
Requires-Python: >= 3.9
License-File: LICENSE
License-File: NOTICE
Requires-Dist: clamd>=1.0.2
Dynamic: license-file
Dynamic: requires-python
